README.md
setup.py
nest_logger.egg-info/PKG-INFO
nest_logger.egg-info/SOURCES.txt
nest_logger.egg-info/dependency_links.txt
nest_logger.egg-info/requires.txt
nest_logger.egg-info/top_level.txt
pylogger/__init__.py
pylogger/a.py
pylogger/logger.py