Metadata-Version: 2.1
Name: nest-logger
Version: 1.1.0
Summary: nest common logger
Home-page: UNKNOWN
Author: fuqiang
Author-email: imock@sina.com
License: UNKNOWN
Platform: UNKNOWN
Classifier: Programming Language :: Python :: 3
Classifier: License :: OSI Approved :: MIT License
Classifier: Operating System :: OS Independent
Requires-Python: >=3
